alephzero_bindings.cpython-35m-x86_64-linux-gnu.so
a0/cfg.py
a0/aio.py
a0/remote.py
a0/_opts.py
a0/__init__.py
a0/cli/__init__.py
a0/cli/cmds/cfg.py
a0/cli/cmds/_util.py
a0/cli/cmds/read.py
a0/cli/cmds/log.py
a0/cli/cmds/rpc.py
a0/cli/cmds/pubsub.py
a0/cli/cmds/sub.py
a0/cli/cmds/pub.py
a0/cli/cmds/prpc.py
a0/cli/cmds/__init__.py
a0/cli/cmds/write.py
alephzero-0.3.17.dist-info/top_level.txt
alephzero-0.3.17.dist-info/entry_points.txt
alephzero-0.3.17.dist-info/WHEEL
alephzero-0.3.17.dist-info/METADATA
alephzero-0.3.17.dist-info/RECORD
