Metadata-Version: 2.1
Name: alephzero
Version: 0.3.17
Summary: TODO: description
Home-page: https://github.com/alephzero/py
Author: Leonid Shamis
Author-email: leonid.shamis@gmail.com
License: UNKNOWN
Platform: UNKNOWN
Requires-Dist: click (>=8.0.3)
Requires-Dist: jsonpointer (>=2.1)
Requires-Dist: websocket-client (>=1.2.1)
